{
  "success": true,
  "data": [
      {
          "t_id": 18,
          "unsplash_id": "g_gwdpsCVAY",
          "name": "white and pink petaled flowers on metal fence near concrete houses and tower at daytime",
          "url": "https://images.unsplash.com/photo-1467269204594-9661b134dd2b?crop=entropy&cs=tinysrgb&fit=max&fm=jpg&ixid=M3w2NzIwNjh8MHwxfHNlYXJjaHwxfHxnZXJtYW55fGVufDB8MHx8fDE3MzA5NDk3MDh8MA&ixlib=rb-4.0.3&q=80&w=1080&w=500&h=350",
          "author": "Roman Kraft",
          "author_url": "https://api.unsplash.com/users/iamromankraft"
      },
      {
          "t_id": 18,
          "unsplash_id": "tn2rBnvIl9I",
          "name": "white concrete castle in green field",
          "url": "https://images.unsplash.com/photo-1449452198679-05c7fd30f416?crop=entropy&cs=tinysrgb&fit=max&fm=jpg&ixid=M3w2NzIwNjh8MHwxfHNlYXJjaHwyfHxnZXJtYW55fGVufDB8MHx8fDE3MzA5NDk3MDh8MA&ixlib=rb-4.0.3&q=80&w=1080&w=500&h=350",
          "author": "Rachel Davis",
          "author_url": "https://api.unsplash.com/users/rmaedavis"
      },
      {
          "t_id": 18,
          "unsplash_id": "2qguco4_iaE",
          "name": "duck standing on brown rock",
          "url": "https://images.unsplash.com/photo-1543169108-32ac15a21e05?crop=entropy&cs=tinysrgb&fit=max&fm=jpg&ixid=M3w2NzIwNjh8MHwxfHNlYXJjaHwzfHxnZXJtYW55fGVufDB8MHx8fDE3MzA5NDk3MDh8MA&ixlib=rb-4.0.3&q=80&w=1080&w=500&h=350",
          "author": "Daniel Seßler",
          "author_url": "https://api.unsplash.com/users/danielsessler"
      },
      {
          "t_id": 18,
          "unsplash_id": "UdQ4SdV9UE8",
          "name": "white castle surround by green trees during daytime",
          "url": "https://images.unsplash.com/photo-1458107768117-48f4877a125a?crop=entropy&cs=tinysrgb&fit=max&fm=jpg&ixid=M3w2NzIwNjh8MHwxfHNlYXJjaHw0fHxnZXJtYW55fGVufDB8MHx8fDE3MzA5NDk3MDh8MA&ixlib=rb-4.0.3&q=80&w=1080&w=500&h=350",
          "author": "Ashley Knedler",
          "author_url": "https://api.unsplash.com/users/ashkned"
      },
      {
          "t_id": 18,
          "unsplash_id": "2cRXSWyMHA8",
          "name": "green trees during daytime",
          "url": "https://images.unsplash.com/photo-1504279577054-acfeccf8fc52?crop=entropy&cs=tinysrgb&fit=max&fm=jpg&ixid=M3w2NzIwNjh8MHwxfHNlYXJjaHw1fHxnZXJtYW55fGVufDB8MHx8fDE3MzA5NDk3MDh8MA&ixlib=rb-4.0.3&q=80&w=1080&w=500&h=350",
          "author": "Sven Wilhelm",
          "author_url": "https://api.unsplash.com/users/svenwilhelm"
      },
      {
          "t_id": 18,
          "unsplash_id": "g_DTWgRypfE",
          "name": "low-angle photography of building",
          "url": "https://images.unsplash.com/photo-1531077386034-d12285794b5c?crop=entropy&cs=tinysrgb&fit=max&fm=jpg&ixid=M3w2NzIwNjh8MHwxfHNlYXJjaHw2fHxnZXJtYW55fGVufDB8MHx8fDE3MzA5NDk3MDh8MA&ixlib=rb-4.0.3&q=80&w=1080&w=500&h=350",
          "author": "Thanos Pal",
          "author_url": "https://api.unsplash.com/users/thanospal"
      },
      {
          "t_id": 18,
          "unsplash_id": "iPOZf3tQfHA",
          "name": "time-lapse photography of vehicle at the road in between the building at nighttime aerial photography",
          "url": "https://images.unsplash.com/photo-1528728329032-2972f65dfb3f?crop=entropy&cs=tinysrgb&fit=max&fm=jpg&ixid=M3w2NzIwNjh8MHwxfHNlYXJjaHw3fHxnZXJtYW55fGVufDB8MHx8fDE3MzA5NDk3MDh8MA&ixlib=rb-4.0.3&q=80&w=1080&w=500&h=350",
          "author": "Stephan Widua",
          "author_url": "https://api.unsplash.com/users/stewi"
      },
      {
          "t_id": 18,
          "unsplash_id": "mtfTz0FnwBw",
          "name": "brown concrete gateway during daytime",
          "url": "https://images.unsplash.com/photo-1554072675-66db59dba46f?crop=entropy&cs=tinysrgb&fit=max&fm=jpg&ixid=M3w2NzIwNjh8MHwxfHNlYXJjaHw4fHxnZXJtYW55fGVufDB8MHx8fDE3MzA5NDk3MDh8MA&ixlib=rb-4.0.3&q=80&w=1080&w=500&h=350",
          "author": "Ansgar Scheffold",
          "author_url": "https://api.unsplash.com/users/ansgarscheffold"
      },
      {
          "t_id": 18,
          "unsplash_id": "Xhl3pnhY9lY",
          "name": "london bridge during night time",
          "url": "https://images.unsplash.com/photo-1617394557915-fdf2a65fcfec?crop=entropy&cs=tinysrgb&fit=max&fm=jpg&ixid=M3w2NzIwNjh8MHwxfHNlYXJjaHw5fHxnZXJtYW55fGVufDB8MHx8fDE3MzA5NDk3MDh8MA&ixlib=rb-4.0.3&q=80&w=1080&w=500&h=350",
          "author": "Maciej Ruminkiewicz",
          "author_url": "https://api.unsplash.com/users/mruminkiewicz"
      },
      {
          "t_id": 18,
          "unsplash_id": "QICQFkZp0Aw",
          "name": "white castle on snow mountain under clear blue sky",
          "url": "https://images.unsplash.com/photo-1548783094-f92d7c8ae2d3?crop=entropy&cs=tinysrgb&fit=max&fm=jpg&ixid=M3w2NzIwNjh8MHwxfHNlYXJjaHwxMHx8Z2VybWFueXxlbnwwfDB8fHwxNzMwOTQ5NzA4fDA&ixlib=rb-4.0.3&q=80&w=1080&w=500&h=350",
          "author": "Bharat Patil",
          "author_url": "https://api.unsplash.com/users/bharat_patil_photos"
      }
  ],
  "message": "Unsplash Images"
}